segmock/__init__.py
segmock/__main__.py
segmock/app.py
segmock/app.tcss
segmock/blocking_screen.py
segmock/clock.py
segmock/py.typed
segmock/stopwatch.py
segmock/version.py
segmock/font/7segment.flf
segmock-0.2.0.dist-info/METADATA
segmock-0.2.0.dist-info/WHEEL
segmock-0.2.0.dist-info/entry_points.txt
segmock-0.2.0.dist-info/licenses/LICENSE
segmock-0.2.0.dist-info/RECORD
