Metadata-Version: 2.4
Name: segmock
Version: 0.2.0
Summary: 7-segment clock (segmock)
Project-URL: Homepage, https://github.com/sou-san/segmock
Project-URL: Repository, https://github.com/sou-san/segmock
Project-URL: Issues, https://github.com/sou-san/segmock/issues
Project-URL: Documentation, https://github.com/sou-san/segmock/blob/main/README.md
Author-email: sou-san <sou887867@gmail.com>
License: MIT License
License-File: LICENSE
Keywords: 7-segment,cli,clock,segmock,simple,stopwatch,terminal,tool,tui
Classifier: Development Status :: 3 - Alpha
Classifier: Environment :: Console
Classifier: Intended Audience :: End Users/Desktop
Classifier: License :: OSI Approved :: MIT License
Classifier: Natural Language :: English
Classifier: Operating System :: Microsoft :: Windows :: Windows 10
Classifier: Operating System :: Microsoft :: Windows :: Windows 11
Classifier: Operating System :: POSIX :: Linux
Classifier: Programming Language :: Python :: 3
Classifier: Programming Language :: Python :: 3.10
Classifier: Programming Language :: Python :: 3.11
Classifier: Programming Language :: Python :: 3.12
Classifier: Programming Language :: Python :: 3.13
Classifier: Typing :: Typed
Requires-Python: >=3.10
Requires-Dist: click<9.0.0,>=8.1.8
Requires-Dist: textual-pyfiglet==0.5.5
Requires-Dist: textual<4.0.0,>=3.1.1
